Workbook

Sheet PROJ.VIABILIDADE
A1: RESSARCIMENTO CUSTOS ESTUDO DE VIABILIDADE
A2: ITEM | B2: REFERÊNCIA | C2: DISCRIMINAÇÃO | D2: UND | E2: QUANTIDADE | F2: PREÇO UNITÁRIO | H2: P. TOTAL
F3: SEM BDI | G3: COM BDI
B4: ADMINISTRAÇÃO
A5: 0.1 | B5: 1 | C5: ELABORAÇÃO DE ESTUDOS E PROJETOS - VIABILIDADE | E5: 1 | F5: 1000000 | G5: 1258000 | H5: =G5*E5 -> 1258000
F6: Total do item 0.1 | H6: =SUM(H5:H5) -> 1258000
A8: Total do item 0.1 | G8: =SUM(H6) -> 1258000

Sheet 1.0 PLANILHA ORÇAMENTARIA
A1: PREFEITURA MUNICIPAL DE CAMPOS DOS GOYTACAZES USINA SOLAR FOTOVOLTAICA PLANILHA ORÇAMENTÁRIA
A2: PLANILHA ORÇAMENTÁRIA
A3: DADOS DA OBRA
A4: NOME: USINA SOLAR FOTOVOLTAICA CAMPOS DOS GOYTACAZES - RJ | D4: TIPO DE INTERVENÇAO: CONSTRUÇÃO | G4: BDI: | H4: FONTE: SINAPI 2021
A6: ENDEREÇO: CAMPOS DOS GOYTACAZES | D6: ÁREA: 400.000,00 m2 | G6: 0.2583
A7: 1 SERVIÇOS PRELIMINARES
A8: ITEM | B8: REFERÊNCIA | C8: DISCRIMINAÇÃO | D8: UND | E8: QUANTIDADE | F8: PREÇO UNITÁRIO | H8: P. TOTAL
F9: SEM BDI | G9: COM BDI
A10: 1.1 | B10: 93584 | C10: EXECUÇAO DE DEP SITO EM CANTEIRO DE OBRA EM CHAPA DE MADEIRA COMPENSAD A, NÃO INCLUSO MOBILIÁRIO. | E10: 16 | F10: 700.18 | G10: 881 | H10: =G10*E10 -> 14096
A13: 1.2 | B13: 93208 | C13: EXECUÇÃO DE ALMOXARIFADO EM CANTEIRO DE OBRA EM CHAPA DE MADEIRA COMPE NSADA, INCLUSO PRATELEIRAS. AF_02/2016 | E13: 20 | F13: 725.17 | G13: 912.44 | H13: =G13*E13 -> 18248.8
A16: 1.3 | B16: 4813 | C16: PLACA DE OBRA (PARA CONSTRUCAO CIVIL) EM CHAPA GALVANIZADA *N. 22*, ADESIVADA, M2 225,00 | E16: 6 | F16: 225 | G16: 283.1 | H16: =G16*E16 -> 1698.6
A18: 1.4 | B18: COMPOSIÇÃO | C18: DE X 1,125* M (SEM POSTES PARA FIXACAO) | E18: 194 | F18: R$ 8 60 | G18: 10.82 | H18: =G18*E18 -> 2099.08
A20: 1.5 | B20: COMPOSIÇÃO | C20: ELABORAÇÃO DE PROJETOS HIDROSSANITÁRIOS, INCLUINDO PLUVIAL PARA EDIFICAÇÕES NOVAS | D20: IT12 | E20: 194 | F20: 5.5 | G20: 6.92 | H20: =G20*E20 -> 1342.48
A21: 1.6 | B21: COMPOSIÇÃO | C21: ELABORAÇ O DE PROJETOS DE AR CONDICIONADO, INCLUINDO DRENAGEM, PARA EDIFICA ÓES NOVAS | E21: 194 | F21: 2 | G21: 2.51 | H21: =G21*E21 -> 486.94
A23: 1.7 | B23: COMPOSIÇÃO | C23: PROJETO ARQUITETONICO DE EDIFICAÇOES NOVAS | E23: 194 | F23: 25 | G23: 31.45 | H23: =G23*E23 -> 6101.3
A24: 1.8 | B24: IBEC | C24: PROJETO EIÉTRICO | F24: 40000 | G24: 50330.2 | H24: =G24 -> 50330.2
A27: 1.9 | B27: COMPOSIÇÃO | C27: ELABORAÇAO DE PROJETO ARQUITETONICO URBANISTICO (INCLUINDO TOPOGRAFIA, PROJETO URBANISTICO, REGULARIZAÇÃO DOS PARCELAMENTOS DE SOLO, PROJETOS PAVIMENTA Ao, SINALIZA Ao DE TRÂNSITO PAISAGíSTlCO, URBANISTICO, DRENAGEM, | E27: 400000 | G27: 1.63 | H27: =G27*E27 -> 652000
F33: TOTAL ITEM 1 | H33: =SUM(H10:H32) -> 746403.4

Sheet 2.0 MOVIMENTO DE TERRA E DREN
A1: 2 MOVIMENTO DE TERRA E DRENAGEM
A3: ITEM | B3: REFERÊNCIA | C3: DISCRIMINAÇÃO | D3: UND | E3: QUANTIDADE | F3: PREÇO UNITÁRIO | H3: P. TOTAL
F4: SEM BDI | G4: COM BDI
A5: 2.1 | B5: 98525 | C5: LIMPEZA MECANIZADA DE CAMADA VEGETAL, VEGETAÇÃO E PEQUENAS ÁRVORES (DIAMETRO DE TRONCO MENOR QUE 0,20M) COM TRATOR DE ESTEIRA. AF 05/2018 | D5: mg | E5: 400000 | F5: 0.27 | G5: 0.33 | H5: =G5*E5 -> 132000
A7: 2.2 | B7: 6081 | C7: ARGILA OU BARRO PARA ATERRO/REATERRO .COM TRANSPORTE ATÉ IOKM) | E7: 80000 | F7: 29.31 | G7: 36.87 | H7: =G7*E7 -> 2949600
A9: 2.3 | B9: 93358 | C9: ESCAVAÇAO MANUAL DE VALA COM PROFUNDIDADE MENOR OU IGUALA 1,30 M. AF 02/2021 | E9: 2000 | F9: 55.46 | G9: 69.78 | H9: =G9*E9 -> 139560
A10: 2.4 | B10: 53527 | C10: REATERRO APILOADO DE VALA COM MATERIAL DA OBRA | E10: 1000 | F10: 74.88 | G10: 94.21 | H10: =G10*E10 -> 94210
A12: 2.5 | B12: 79472 | C12: REGULARIZAÇÃO DE SUPERFÍCIES COM MOTONIVELADORA. AF_11/2019 | E12: 400000 | F12: 0.08 | G12: 0.1 | H12: =G12*E12 -> 40000
F14: Total do item 2 | H14: =SUM(H5:H13) -> 3355370

Sheet 3.1 CERCAMENTO DO TERRENO
A1: 3 CERCAMENTO DO TERRENO
A3: ITEM | B3: REFERÊNCIA | C3: DISCRIMINAÇÃO | D3: UND | E3: QUANTIDADE | F3: PREÇO UNITÁRIO | H3: P. TOTAL
F4: SEM BDI | G4: COM BDI
A5: 3.1 | B5: 93205 | C5: ALAMBRADO EM MOURÕES DE CONCRETO COM TELA DE ARAME GALVANIZADO (INLCUSIVE MURETA EM CONCRETO). AF 05/2018 | D5: M | E5: 2532 | F5: 116.2 | G5: 146.2 | H5: =G5*E5 -> 370178.4
A7: 3.2 | B7: 37562 | C7: PORTÃO DE CORRER EM GRADIL FIXO DE BARRA DE FERRO CHATA DE 3 X 1/4" NA VERTICAL, SEM REQUADRO, ACABAMENTO NATURAL, COM TRILHOS E ROLDANAS | E7: 10 | F7: 620.63 | G7: 780.91 | H7: =G7*E7 -> 7809.1
A9: 3.3 | B9: 101188 | C9: RECOMPOSIÇÃO PARCIAL DE ARAME FARPADON0 14 CAKSSE 250, FIXADO EM CERCA COM MOURÕES DE CONCRETO - FORNECIMENTO E INSTALAÇÃO. AF 05/2020 | D9: M | E9: 2532 | F9: 25 | G9: 31.25 | H9: =G9*E9 -> 79125
F11: Total do item 3 | H11: =SUM(H5:H10) -> 457112.5

Sheet 4.1 FUNDAÇÃO ESTRUTURAS PAINEIS
A1: 4 FUNDAÇÃO DAS ESTRUTURAS DOS PAINÉIS
A3: ITEM | B3: REFERÊNCIA | C3: DISCRIMINAÇÃO | D3: UND | E3: QUANTIDADE | F3: PREÇO UNITÁRIO | H3: P. TOTAL
F4: SEM BDI | G4: COM BDI
A5: 4.1 | B5: 101176 | C5: ESTACA BROCA DE CONCRETO, DIÂMETRO DE 30CM, ESCAVAÇÃO COM TRADO CONCHA, INTEIRAMENTE ARMADA. AF_05/2020 | D5: M | E5: 74100 | F5: 129.34 | G5: 162.74 | H5: =G5*E5 -> 12059034
A8: 4.2 | B8: 99062 | C8: MARCAÇÃO DE PONTOS EM GABARITO OU CAVALTE. AF_10/2018 | D8: und | E8: 7600 | F8: 1.66 | G8: 2.08 | H8: =G8*E8 -> 15808
F10: Total do item 4 | H10: =SUM(H5:H9) -> 12074842

Sheet 5.1 EDIFICIOS ESCRITÓRIO E ALMO
A1: 5.1 EDIFICIOS ESCRITÓRIO E ALMOXARIFADO
A3: ITEM | B3: REFERÊNCIA | C3: DISCRIMINAÇÃO | D3: UND | E3: QUANTIDADE | F3: PREÇO UNITÁRIO | H3: P. TOTAL
F4: SEM BDI | G4: COM BDI
A5: 5.1 | B5: FUNDAÇÕES E ESTRUTURAS
A6: 5.1.1 | B6: 87690 | C6: CONTRAPISO EM ARGAMASSA TRAÇO (CIMENTO E AREIA), PREPARO MECÂNICO COM BETONEIRA 400 L, APLICADO EM ÁREAS SECAS SOBRE LAJE, NÃO ADERIDO, ESPESSURA 5CM AF 06/2014 | D6: m2 | E6: 98.1 | F6: 35.33 | G6: 44.45 | H6: =G6*E6 -> 4360.545
A9: 5.1.2 | B9: 87246 | C9: REVESTIMENTO CERAMICO PARA PISO COM PLACAS TIPO GRÉS DE DIMENSÕES 35X35 CM APLICADA EM AMBIENTES DE ÁREA MENOR QUE 5 rv12 | D9: m2 | E9: 72.47 | F9: 50.56 | G9: 63.61 | H9: =G9*E9 -> 4609.8167
A12: 5.1.3 | B12: 88648 | C12: RODAPE CERAMICO DE 7CM DE ALTURA COM PLACAS TIPO GRÉS DE DIMENSÕES 35X 35CM. AF 06/2014 | D12: M | E12: 90.8 | F12: 6.02 | G12: 7.57 | H12: =G12*E12 -> 687.356
A14: 5.1.4 | B14: 92775 | C14: ARMAÇÃO DE PILAR OU VIGA DE UMA ESTRUTURA CONVENCIONAL DE CONCRETO ARM ADO EM UMA EDIFiCAÇÃO TÉRREA OU SOBRADO UTILIZANDO AÇO CA-60 DE 5.0 MM - MONTAGEM. AF_12/2015 | D14: KG | E14: 947.59 | F14: 19.21 | G14: 24.17 | H14: =G14*E14 -> 22903.25
A17: 5.1.5 | B17: 92779 | C17: ARMAÇÃO DE PILAR OU VIGA DE UMA ESTRUTURA CONVENCIONAL DE CONCRETO ARM ADO EM UMA EDIFíCAÇÃO TÉRREA OU SOBRADO UTILIZANDO AÇO CA-50 DE 12.5 M M - MONTAGEM | D17: KG | E17: 771.23 | F17: 13.99 | G17: 17.6 | H17: =G17*E17 -> 13573.648
A21: 5.1.6 | B21: 94964 | C21: CONCRETO FCK 20MPA, TRAÇO (CIMENTO/ AREIA MÉDIA] BRITA 1) - PREPARO MECÂNICO COM BETONEIRA 400 L. AF_07/2016 | E21: 11.35 | F21: 371.92 | G21: 467.97 | H21: =G21*E21 -> 5311.4595
F24: Total do item 5.1 | H24: =SUM(H5:H23) -> 51446.076

Sheet 5.2 REVESTIMENTO DE PAREDES
A1: 5.2 REVESTIMENTO DE PAREDES E LAJES
A3: ITEM | B3: REFERÊNCIA | C3: DISCRIMINAÇÃO | D3: UND | E3: QUANTIDADE | F3: PREÇO UNITÁRIO | H3: P. TOTAL
F4: SEM BDI | G4: COM BDI
A5: 5.2 | B5: REVESTIMENTO DE PAREDES E LAJES
A6: 5.2.1 | B6: 87878 | C6: CHAPISCO APLICADO EM ALVENARIAS E ESTRUTURAS DE CONCRETO INTERNAS, COM COLHER DE PEDREIRO. ARGAMASSA TRAÇO COM PREPARO MANUAL. AF 06/20 14 | E6: 286.4 | F6: 3.44 | G6: 4.32 | H6: =G6*E6 -> 1237.248
A10: 5.2.2 | B10: 87264 | C10: REVESTIMENTO CERAMICO PARA PAREDES INTERNAS COM PLACAS TIPO GRÉS OU SEMl-GRÉS DE DIMENSÕES CM APLICADAS EM AMBIENTES DE ÁREA MENOR QUE 5 M2 NA ALTURA INTEIRA DAS PAREDES. AF 06/2014 | D10: m2 | E10: 84.3 | F10: 55.08 | G10: 69.3 | H10: =G10*E10 -> 5841.99
F14: Total do item 5.2 | H14: =SUM(H6:H13) -> 7079.238

Sheet 5.3 ESQUADRIAS DE MADEIRA
A1: 5.3 ESQUADRIAS DE MADEIRA
A3: ITEM | B3: REFERÊNCIA | C3: DISCRIMINAÇÃO | D3: UND | E3: QUANTIDADE | F3: PREÇO UNITÁRIO | H3: P. TOTAL
F4: SEM BDI | G4: COM BDI
A5: 5.3 | B5: ESQUADRIAS DE MADEIRA
A6: 5.3.1 | B6: 90822 | C6: PORTA DE MADEIRA PARA PINTURA, SEMI-OCA (LEVE OU MÉDIA), 80X210CM, ESP ESSURA DE 3,5CM, INCLUSO DOBRADIÇAS - FORNECIMENTO E INSTALAÇÃO. AF 08 12015 | D6: und | E6: 2 | F6: 300.67 | G6: 378.31 | H6: =G6*E6 -> 756.62
A10: 5.3.2 | B10: 91306 | C10: FECHADURA DE EMBUTIR PARA PORTAS INTERNAS, COMPLETA, ACABAMENTO PADRÃO MÉDIO, COM EXECUÇÃO DE FURO - FORNECIMENTO E INSTALAÇÃO. AF 08/2015 | D10: und | E10: 6 | F10: 123.73 | G10: 155.68 | H10: =G10*E10 -> 934.08
A14: 5.3.3 | B14: 102180 | C14: INSTALAÇÃO DE VIDRO TEMPERADO, R: IOMM, ENCAIXADO EM PERFIL U. AF 01/2021 P | D14: rn2 | E14: 4.2 | F14: 336, 14 | G14: 422.94 | H14: =G14*E14 -> 1776.348
A16: 5.3.4 | B16: 91341 | C16: PORTA EM ALUMÍNIO DE ABRIR TIPO VENEZIANA COM GUARNIÇÃO, FIXAÇÃO COM PARAFUSOS FORNECIMENTO E INSTALAÇÃO. AF_12/2019 | D16: m2 | E16: 3.78 | F16: 511.57 | G16: 643.68 | H16: =G16*E16 -> 2433.1104
A19: 5.3.5 | B19: 4828 — COMPOSIÇÃO | C19: SOLEIRA/ PEITORIL EM MARMORE, POLIDO, BRANCO COMUM, CM, E: *2* CM, CORTE RETO | E19: 0.84 | F19: 61.3 | G19: 77.13 | H19: =G19*E19 -> 64.7892
F21: Total do item 5.3 | H21: =SUM(H6:H20) -> 5964.9476

Sheet 5.4 PINTURA ACABAMENTO
A1: 5.4 PINTURA/ACABAMENTO
A3: ITEM | B3: REFERÊNCIA | C3: DISCRIMINAÇÃO | D3: UND | E3: QUANTIDADE | F3: PREÇO UNITÁRIO | H3: P. TOTAL
F4: SEM BDI | G4: COM BDI
A5: 5.4 | B5: PINTURA
A6: 5.4.1 | B6: 88497 | C6: APLICAÇÃO E LIXAMENTO DE MASSA LÁTEX EM PAREDES, DUAS DEMÃOS. AF 06/20 14 | D6: m2 | E6: 286.4 | F6: 11 | G6: 14.38 | H6: =G6*E6 -> 4118.432
A8: 5.4.2 | B8: 88488 | C8: APLICAÇAO MANUAL DE PINTURA COM TINTA LÁTEX ACRÍLICA EM TETO, DUAS DEM Aos. AF 06/2014 | D8: m2 | E8: 63.45 | F8: 14.05 | G8: 17.67 | H8: =G8*E8 -> 1121.1615
A10: 5.4.3 | B10: 88489 | C10: APLICAÇÃO DE FUNDO SELADOR ACRÍLICO EM PAREDES, UMA DEMÃO. AF 06/2014 | D10: m2 | E10: 572.8 | F10: 12.71 | G10: 15.99 | H10: =G10*E10 -> 9159.072
A12: 5.4.4 | B12: 102223 | C12: PINTURA EM VERNIZ SINTETICO BRILHANTE EM MADEIRA, TRES DEMAOS | D12: m2 | E12: 8.4 | F12: 21 ,48 | G12: 27.02 | H12: =G12*E12 -> 226.968
F14: Total do item 5.4 | H14: =SUM(H6:H13) -> 14625.633

Sheet 5.5 COBERTURA
A1: 5.5 COBERTURA
A3: ITEM | B3: REFERÊNCIA | C3: DISCRIMINAÇÃO | D3: UND | E3: QUANTIDADE | F3: PREÇO UNITÁRIO | H3: P. TOTAL
F4: SEM BDI | G4: COM BDI
A5: 5.5 | B5: COBERTURA
A6: 5.5.1 | B6: 94216 | C6: TELHAMENTO COM TELHA METALICA TERMOACÚSTICA E = 30 MM, COM ATÉ 2 ÁGUAS INCLUSO I AMENTO. AF 06/2016 | D6: m2 | E6: 107.91 | F6: 230.19 | G6: 289.63 | H6: =G6*E6 -> 31253.973
A9: 5.5.2 | B9: 92606 | C9: FABRICAÇÃO E INSTALAÇÃO DE TESOURA INTEIRA EM AÇO, VÃO DE 5 M, PARA TELHA ONDULADA DE FIBROCIMENTO, METÁLICA, PLASTICA OU TERMOACUSTICA, INCLUSO IÇAMENTO. AF_12/2015 | D9: UND | E9: 7 | F9: 1015.34 | G9: 1277.55 | H9: =G9*E9 -> 8942.85
F13: Total do item 5.5 | H13: =SUM(H6:H12) -> 40196.823

Sheet 5.6 FORROS E DIVISORIAS
A1: 5.6 FORROS E DIVISORIAS
A3: ITEM | B3: REFERÊNCIA | C3: DISCRIMINAÇÃO | D3: UND | E3: QUANTIDADE | F3: PREÇO UNITÁRIO | H3: P. TOTAL
F4: SEM BDI | G4: COM BDI
A5: 5.6 | B5: FORROS E DIVISORIAS
A6: 5.6.1 | B6: 39566 COMPOSIÇÃO | C6: PLACA / CHAPA DE GESSO ACARTONADO, ACABAMENTO VINILICO LISO EM UMA DAS FACES, COR BRANCA, BORDA QUADRADA, E = 9,5 MM, 625 X 625 MM (L X C), PARA FORRO REMOVIVEL | E6: 98.1 | F6: 51.16 | G6: 64.37 | H6: =G6*E6 -> 6314.697
F8: Total do do item 5.6 | H8: =SUM(H6) -> 6314.697

Sheet 5.7 INSTALACOES HIDRAULICAS
A1: 5.7 INSTALACOES HIDRAULICAS
A3: ITEM | B3: REFERÊNCIA | C3: DISCRIMINAÇÃO | D3: UND | E3: QUANTIDADE | F3: PREÇO UNITÁRIO | H3: P. TOTAL
F4: SEM BDI | G4: COM BDI
A5: 5.7 | B5: INSTALACOES HIDRAULICAS
A6: 5.7.1 | B6: 94649 | C6: TUBO, pvc, SOLDÁVEL, DN 32 MM, INSTALADO EM RESERVATORIO DE ÁGUA DE EDIFICIOS QUE POSSUA RESERVATÓRIO DE FIBRA, FORNECIMENTO E INSTALAÇÃO. AF_06/2016 | E6: 12 | F6: 13.45 | G6: 16.92 | H6: =G6*E6 -> 203.04
A9: 5.7.2 | B9: 94651 | C9: TUBO, pvc, SOLDÁVEL, DN 50 MM, INSTALADO EM RESERVAÇÃO DE ÁGUA DE EDIFICIOS QUE POSSUA RESERVATÓRIO DE FIBRA, FORNECIMENTO E INSTALAÇÃO. AF_06/2016 | D9: m | E9: 17 | F9: 21.19 | G9: 26.66 | H9: =G9*E9 -> 453.22
A12: 5.7.3 | B12: 1 1868 COMPOSIÇÃO | C12: CAIXA DE AGUA EM FIBRA DE VIDRO 1000 LITROS, COM TAMPA | D12: und | E12: 1 | F12: 434.3 | G12: 546.46 | H12: =G12*E12 -> 546.46
A13: 5.7.4 | B13: 94495 | C13: REGISTRO GAVETA COM ACABAMENTO E CANOPLA CROMADOS, SIMPLES, BITOLA 1 " (REF 1509 | D13: und | E13: 5 | F13: 29.18 | G13: 36.71 | H13: =G13*E13 -> 183.55
A15: 5.7.5 | B15: 99635 | C15: VALVULA DE DESCARGA METALICA, BASE 1 1/2 " E ACABAMENTO METALICO CROMADO | D15: und | E15: 2 | F15: 174.14 | G15: 219.11 | H15: =G15*E15 -> 438.22
A17: 5.7.6 | B17: 95469 | C17: VASO SANITARIO SIFONADO CONVENCIONAL COM LOUÇA BRANCA - FORNECIMENTO E INSTALAÇÃO. AF 10/2016 | D17: und | E17: 2 | F17: 232.64 | G17: 292.72 | H17: =G17*E17 -> 585.44
A19: 5.7.9 | B19: 86939 | C19: LAVATORIO LOUÇA BRANCA COM COLUNA, X 35,5* CM, PADRÃO POPULAR, INCLUSO SIFÃO FLEXíVEL EM pvc, VÁLVULA E ENGATE FLEXíVEL 30CM EM PLÁSTICO E COM TORNERA CROMADA PADRÃO POPULAR - FORNECIMENTO E INSTALAÇÃO. AF 12/2013 | D19: und | E19: 4 | F19: 315, 14 | G19: 396.52 | H19: =G19*E19 -> 1586.08
A23: 5.7.10 | B23: 98462 | C23: SUPORTE APOIO CAIXA D AGUA BARROTES MADEIRA DE 1000 LITROS. AF_05/2018_P | D23: und | E23: 1 | F23: 5531 | G23: 6960.27 | H23: =G23*E23 -> 6960.27
F24: Total do item 5.7 | H24: =SUM(H6:H23) -> 10956.28

Sheet 5.8 INSTALACOES SANITARIAS PLU
A1: 5.8 INSTALACOES SANITARIAS/PLUVIAIS
A3: ITEM | B3: REFERÊNCIA | C3: DISCRIMINAÇÃO | D3: UND | E3: QUANTIDADE | F3: PREÇO UNITÁRIO | H3: P. TOTAL
F4: SEM BDI | G4: COM BDI
A5: 5.8 | B5: INSTALACOES SANITARIAS/PLUVIAIS
A6: 5.8.1 | B6: 89449 | C6: TUBO pvc, SERIE R, GUA PLUVIAL, DN 50 MM FORNECIDO E INSTALADO EM RA MAL DE ENCAMINHAMENTO. AF 12/2014 | D6: M | E6: 14.4 | F6: 16.72 | G6: 21 | H6: =G6*E6 -> 302.4
A8: 5.8.2 | B8: 89509 | C8: TUBO pvc, SERIE R, AGUA PLUVIAL, DN 50 MM, FORNECIDO E INSTALADO EM RA MAL DE ENCAMINHAMENTO. AF 12/2014 | D8: M | E8: 19.73 | F8: 25.53 | G8: 32.12 | H8: =G8*E8 -> 633.7276
A10: 5.8.3 | B10: 89512 | C10: TUBO pvc, SERIE R, AGUA PLUVIAL, DN 100 MM, FORNECIDO E INSTALADO EM R AMAL DE ENCAMINHAMENTO. AF 12/2014 | D10: M | E10: 158.33 | F10: 60, 55 | G10: 76.18 | H10: =G10*E10 -> 12061.579
A12: 5.8.4 | B12: 98104 | C12: CAIXA DE GORDURA DUPLA EM CONCRETO PREMOLDADO DN 60MM COM TAMPA - FOR NECIMENTO E INSTALACAO | D12: UND | E12: 2 | F12: 346.65 | G12: 436.17 | H12: =G12*E12 -> 872.34
E14: Total do item 5.8 | H14: =SUM(H6:H13) -> 13870.047

Sheet 5.9 INSTALAÇÓES ELÉTRICAS
A1: 5.9 INSTALAÇÓES ELÉTRICAS
A2: ITEM | B2: REFERÊNCIA | C2: DISCRIMINAÇÃO | D2: UND | E2: QUANTIDADE | F2: PREÇO UNITÁRIO | H2: P. TOTAL
F3: SEM BDI | G3: COM BDI
A4: 5.9 | B4: INSTALAÇÓES ELÉTRICAS
A5: 5.9.1 | B5: 91924 | C5: CABO DE COBRE FLEXIVEL ISOLADO, 1,5 MT, ANTI-CHAMA 450/750 V, PARA ClRCUITOS TERMINAS - FORNECIMENTO E INSTALAÇÃO. AF 12/2015 | D5: M | E5: 50.01 | F5: 2.55 | G5: 3.2 | H5: =G5*E5 -> 160.032
A6: 5.9.2 | B6: 91926 | C6: CABO DE COBRE FLEX VEL ISOLADO, MM2 , ANTI-CHAMA 450/750 V, PARA ClRCUITOS TERMINAS - FORNECIMENTO E INSTALAÇÃO. AF 12/2015 | D6: M | E6: 455.09 | F6: 3.78 | G6: 4.75 | H6: =G6*E6 -> 2161.6775
A7: 5.9.3 | B7: 91928 | C7: CABO DE COBRE FLEXíVEL ISOLADO, 4 MM2 , ANTICHAMA 450/750 V, PARA CIRC UITOS TERMINAS FORNECIMENTO E INSTALAÇÃO. AF_12/2015 | D7: M | E7: 35.02 | F7: 6.32 | G7: 7.95 | H7: =G7*E7 -> 278.409
A8: 5.9.4 | B8: 91934 | C8: CABO DE COBRE FLEXiVEL ISOLADO, 16 MM2 ANTICHAMA 450/750 V, PARA CR CUITOS TERMINAS FORNECIMENTO E INSTALAÇÃO. AF_12/2015 | D8: M | E8: 220 | F8: 22.19 | G8: 27.92 | H8: =G8*E8 -> 6142.4
A9: 5.9.5 | B9: 93657 | C9: DISJUNTOR MONOPOLAR TIPO DIN, CORRENTE NOMINAL DE 32A - FORNECIMENTO E INSTALAÇÃO. AF 10/2020 | D9: und | E9: 6 | F9: 13.05 | G9: 16.42 | H9: =G9*E9 -> 98.52
A10: 5.9.6 | B10: 101894 | C10: DISJUNTOR TERMOMAGNETICO TRIPOLAR PADRAO NEMA (AMERICANO) 60 A IOOA 24 OV FORNECIMENTO E INSTALACAO | D10: und | E10: 4 | F10: 140.67 | G10: 176.99 | H10: =G10*E10 -> 707.96
A11: 5.9.7 | B11: 91849 | C11: ELETRODUTO FLEXIVEL CORRUGADO, pvc, DN 32 MM PARA CIRCUITOS TE RMINAIS, INSTALADO EM FORRO - FORNECIMENTO E INSTALAÇÃO AF 12/2015 | D11: M | E11: 598 | F11: 5.67 | G11: 7.13 | H11: =G11*E11 -> 4263.74
A12: 5.9.8 | B12: 97593 | C12: LUMINARIA TIPO SPOT, DE SOBREPOR, COM 1 LÁMPADA FLUORESCENTE DE 15 W, SEM REATOR FORNECIMENTO E INSTALAÇÃO. AF_02/2020 | D12: und | E12: 15 | F12: 123.1 | G12: 154.89 | H12: =G12*E12 -> 2323.35
A13: 5.9.9 | B13: 92023 | C13: INTERRUPTOR SIMPLES (1 MODULO) COM 1 TOMADA DE EMBUTIR 2P+T 10 A, INC LUINDO SUPORTE E PLACA - FORNECIMENTO E INSTALA Ão. AF 12/2015 | D13: und | E13: 36 | F13: 33.59 | G13: 42.26 | H13: =G13*E13 -> 1521.36
A14: 5.9.10 | B14: 92027 | C14: INTERRUPTOR SIMPLES (2 M DULOS) COM 1 TOMADA DE EMBUTIR 2P+T 10 A, IN CLUINDO SUPORTE E PLACA - FORNECIMIENTO E INSTALA Ão. AF 12/2015 | D14: und | E14: 2 | F14: 44.71 | G14: 56.25 | H14: =G14*E14 -> 112.5
A15: 5.9.11 | B15: 101879 | C15: QUADRO DE DISTRIBUIÇÃO DE ENERGIA EM CHAPA DE AÇO GALVANIZADO, DE EMBUTIR, COM BARRAMENTO TRIFÁSICO, PARA 24 DISJUNTORES DIN IODA - FORNECIMENTO E INSTALAÇÃO. AF 10/2020 | D15: und | E15: 2 | F15: 588.48 | G15: 740.45 | H15: =G15*E15 -> 1480.9
A16: 5.9.12 | B16: 100557 | C16: CAIXA DE PASSAGEM PARA TELEFONE 80X80X15CM (SOBREPOR) FORNECIMENTO E INSTALACAO, AF 11/2019 | D16: und | E16: 2 | F16: 483.28 | G16: 608.08 | H16: =G16*E16 -> 1216.16
E17: Total do item 5.9 | H17: =SUM(H5:H16) -> 20467.009

Sheet 5.10 CALÇADA EXTERNA
A1: 5.10 CALÇADA EXTERNA
A2: ITEM | B2: REFERÊNCIA | C2: DISCRIMINAÇÃO | D2: UND | E2: QUANTIDADE | F2: PREÇO UNITÁRIO | H2: P. TOTAL
F3: SEM BDI | G3: COM BDI
A4: 5.10 | B4: CALÇADA EXTERNA
A5: 5.10.1 | B5: 92397 | C5: EXECUÇÃO DE PÁTIO/ESTACIONAMENTO EM PISO INTERTRAVADO, COM BLOCO RETANGULAR COR NATURAL DE 20 X 10 CM, ESPESSURA 6 CM. | E5: 95 | F5: 60.97 | G5: 76.71 | H5: =G5*E5 -> 7287.45
A6: 5.10.2 | B6: 92400 | C6: EXECUÇÃO DE PÁTIO/ESTACIONAMENTO EM PISO INTERTRAVADO, COM BLOCO RETANGULAR COR NATURAL DE 20 X 10 CM, ESPESSURA 10 CM. | E6: 172.82 | F6: 92.4 | G6: 116.26 | H6: =G6*E6 -> 20092.053
A7: 5.10.3 | B7: 98504 | C7: PLANTIO DE GRAMA EM PLACAS. AF_05/2018 | E7: 5563.35 | F7: 11.42 | G7: 14.36 | H7: =G7*E7 -> 79889.706
A8: 5.10.4 | B8: 94265 | C8: GUIA (MEIO-FIO) CONCRETO, MOLDADA IN LOCO COM EXTRUSORA 14 CM BASE X 30 CM ALTURA | D8: m | E8: 58.3 | F8: 38.16 | G8: 48.01 | H8: =G8*E8 -> 2798.983
E9: Total do item 5.10 | H9: =SUM(H5:H8) -> 110068.19
A11: TOTAL DO ITEM 5 | H11: =SUM(H9+'5.9 INSTALAÇÓES ELÉTRICAS'!H17+'5.8 INSTALACOES SANITARIAS PLU'!H14+'5.7 INSTALACOES HIDRAULICAS'!H24+'5.6 FORROS E DIVISORIAS'!H8+'5.5 COBERTURA'!H13+'5.4 PINTURA ACABAMENTO'!H14+'5.3 ESQUADRIAS DE MADEIRA'!H21+'5.2 REVESTIMENTO DE PAREDES'!H14+'5.1 EDIFICIOS ESCRITÓRIO E ALMO'!H24) -> 280988.94

Sheet 6.1 EDIFÍCIO CASA DE FORÇA
A1: 6. EDIFÍCIO CASA DE FORÇA (INVERSORES)
A2: ITEM | B2: REFERÊNCIA | C2: DISCRIMINAÇÃO | D2: UND | E2: QUANTIDADE | F2: PREÇO UNITÁRIO | H2: P. TOTAL
F3: SEM BDI | G3: COM BDI
A4: 6.1 | B4: EDIFÍCIO CASA DE FORÇA (INVERSORES)
A5: 6.1.1 | B5: 87690 | C5: CONTRAPISO EM ARGAMASSA TRAÇO (CIMENTO E AREIA), PREPARO MECÂNICO COM BETONEIRA 400 L, APLICADO EM ÁREAS SECAS SOBRE LAJE, NÃO ADERIDO, ESPESSURA 5CM AF 06/2014 | D5: m² | E5: 96 | F5: 35.33 | G5: 44.45 | H5: =G5*E5 -> 4267.2
A6: 6.1.2 | B6: 87246 | C6: REVESTIMENTO CERÂMICO PARA PISO COM PLACAS TIPO GRÉS DE DIMENSÕES 35X35 CM APLICADA EM AMBIENTES DE ÁREA MENOR QUE 5 | D6: m² | E6: 88.65 | F6: 50.56 | G6: 63.61 | H6: =G6*E6 -> 5639.0265
A7: 6.1.3 | B7: 00C40 | C7: RODAPÉ CERÂMICO DE 7CM DE ALTURA COM PLACAS TIPO GRÉS DE DIMENSÕES 35CM. AF 06/2014 | D7: m | E7: 48.4 | F7: 6.02 | G7: 7.57 | H7: =G7*E7 -> 366.388
A8: 6.1.4 | B8: 92775 | C8: ARMAÇÃO DE PILAR OU VIGA DE UMA ESTRUTURA CONVENCIONAL DE CONCRETO ARMADO EM UMA EDIFICAÇÃO TÉRREA OU SOBRADO UTILIZANDO AÇO CA-60 DE 5.0 MM - MONTAGEM. AF_12/2015 | D8: kg | E8: 365 | F8: 19.21 | G8: 24.17 | H8: =G8*E8 -> 8822.05
A9: 6.1.5 | B9: 92779 | C9: ARMAÇÃO DE PILAR OU VIGA DE UMA ESTRUTURA CONVENCIONAL DE CONCRETO ARMADO EM UMA EDIFICAÇÃO TÉRREA OU SOBRADO UTILIZANDO AÇO CA-50 DE 12.5 MM - MONTAGEM. | D9: kg | E9: 226.39 | F9: 13.99 | G9: 17.6 | H9: =G9*E9 -> 3984.464
A10: 6.1.6 | B10: 94964 | C10: CONCRETO FCK = 20MPA, TRAÇO (CIMENTO/AREIA MÉDIA/BRITA 1) - PREPARO MECÂNICO COM BETONEIRA 400 L. AF_07/2016 | D10: m³ | E10: 7.86 | F10: 371.92 | G10: 467 | H10: =G10*E10 -> 3670.62
E11: Total do item 6.1 | H11: =SUM(H5:H10) -> 26749.749

Sheet 6.2 REVESTIMENTO DE PAREDES
A1: 6.2 REVESTIMENTO DE PAREDES E LAJES
A2: ITEM | B2: REFERÊNCIA | C2: DISCRIMINAÇÃO | D2: UND | E2: QUANTIDADE | F2: PREÇO UNITÁRIO | H2: P. TOTAL
F3: SEM BDI | G3: COM BDI
A4: 6.2 | B4: REVESTIMENTO DE PAREDES E LAJES
A5: 6.2.1 | B5: 87878 | C5: CHAPISCO APLICADO EM ALVENARIAS E ESTRUTURAS DE CONCRETO INTERNAS, COM COLHER DE PEDREIRO. ARGAMASSA TRAÇO COM PREPARO MANUAL. AF 06/2014 | D5: m² | E5: 531 | F5: 3.44 | G5: 4.32 | H5: =G5*E5 -> 2293.92
E6: Total do item 6.2 | H6: =SUM(H5) -> 2293.92

Sheet 6.3 ESQUADRIAS DE VIDROS
A1: 6.3 ESQUADRIAS DE VIDROS
A2: ITEM | B2: REFERÊNCIA | C2: DISCRIMINAÇÃO | D2: UND | E2: QUANTIDADE | F2: PREÇO UNITÁRIO | H2: P. TOTAL
F3: SEM BDI | G3: COM BDI
A4: 6.3 | B4: ESQUADRIAS DE VIDROS
A5: 6.3.1 | B5: 102180 | C5: INSTALAÇÃO DE VIDRO TEMPERADO, IOMM, ENCAIXADO EM PERFIL U. AF 01/2021 P | D5: m² | E5: 7.92 | F5: 336.14 | G5: 422.94 | H5: =G5*E5 -> 3349.6848
A6: 6.3.2 | B6: 4828 COMPOSIÇÃO | C6: SOLEIRA/ PEITORIL EM MÁRMORE, POLIDO, BRANCO COMUM, CM, E: CM, CORTE RETO | D6: m | E6: 0.64 | F6: 61.3 | G6: 77.13 | H6: =G6*E6 -> 49.3632
E7: Total do item 6.3 | H7: =SUM(H5:H6) -> 3399.048

Sheet 6.4 PINTURA
A1: 6.4 PINTURA/PREPARAÇÃO
A2: ITEM | B2: REFERÊNCIA | C2: DISCRIMINAÇÃO | D2: UND | E2: QUANTIDADE | F2: PREÇO UNITÁRIO | H2: P. TOTAL
F3: SEM BDI | G3: COM BDI
A4: 6.4 | B4: PINTURA/PREPARAÇÃO
A5: 6.4.1 | B5: 88497 | C5: APLICAÇÃO E LIXAMENTO DE MASSA LÁTEX EM PAREDES, DUAS DEMÃOS. AF 06/2014 | D5: m² | E5: 531 | F5: 11.47 | G5: 14.43 | H5: =G5*E5 -> 7662.33
A6: 6.4.2 | B6: 88488 | C6: APLICAÇÃO MANUAL DE PINTURA COM TINTA LÁTEX ACRÍLICA EM TETO, DUAS DEMÃOS. AF 06/2014 | D6: m² | E6: 88.65 | F6: 14.05 | G6: 17.67 | H6: =G6*E6 -> 1566.4455
A7: 6.4.3 | B7: 88489 | C7: APLICAÇÃO DE FUNDO SECADOR ACRÍLICO EM PAREDES, UMA DEMÃO. AF 06/2014 | D7: m² | E7: 531.9 | F7: 12.71 | G7: 15.99 | H7: =G7*E7 -> 8505.081
E8: Total do item 6.4 | H8: =SUM(H5:H7) -> 17733.857

Sheet 6.5 COBERTURA
A1: 6.5 COBERTURA
A2: ITEM | B2: REFERÊNCIA | C2: DISCRIMINAÇÃO | D2: UND | E2: QUANTIDADE | F2: PREÇO UNITÁRIO | H2: P. TOTAL
F3: SEM BDI | G3: COM BDI
A4: 6.5 | B4: COBERTURA
A5: 6.5.1 | B5: 94216 | C5: TELHAMENTO COM TELHA METÁLICA TERMOACÚSTICA E = 30 MM, COM ATÉ 2 ÁGUAS INCLUSO IÇAMENTO. AF 06/2016 | D5: m² | E5: 105.6 | F5: 230.19 | G5: 289.63 | H5: =G5*E5 -> 30584.928
A6: 6.5.2 | B6: 92606 | C6: FABRICAÇÃO E INSTALAÇÃO DE TESOURA INTERA EM AÇO, VÃO DE 5 M, PARA TELHA ONDULADA DE FIBROCIMENTO, METÁLICA, PLÁSTICA OU TERMOACÚSTICA, INCLUSO IÇAMENTO. AF_12/2015 | D6: UND | E6: 5 | F6: 1015.34 | G6: 1277.55 | H6: =G6*E6 -> 6387.75
E7: Total do item 6.5 | H7: =SUM(H5:H6) -> 36972.678

Sheet 6.6 DIVISÓRIAS ACARTONADA
A1: 6.6 DIVISÓRIAS ACARTONADA
A2: ITEM | B2: REFERÊNCIA | C2: DISCRIMINAÇÃO | D2: UND | E2: QUANTIDADE | F2: PREÇO UNITÁRIO | H2: P. TOTAL
F3: SEM BDI | G3: COM BDI
A4: 6.6 | B4: DIVISÓRIAS ACARTONADA
A5: 6.6.1 | B5: 39566 COMPOSIÇÃO | C5: PLACA / CHAPA DE GESSO ACARTONADO, ACABAMENTO VINÍLICO LISO EM UMA DAS FACES, COR BRANCA, BORDA QUADRADA, E = 9,5 MM, 625 X 625 MM (L X C), PARA FORRO REMOVÍVEL | D5: m² | E5: 96 | F5: 51.16 | G5: 64.37 | H5: =G5*E5 -> 6179.52
E6: Total do item 6.6 | H6: =SUM(H5) -> 6179.52

Sheet 6.7 INSTALAÇÕES AR CONDICIONADO
A1: 6.7 INSTALAÇÕES AR CONDICIONADO
A2: ITEM | B2: REFERÊNCIA | C2: DISCRIMINAÇÃO | D2: UND | E2: QUANTIDADE | F2: PREÇO UNITÁRIO | H2: P. TOTAL
F3: SEM BDI | G3: COM BDI
A4: 6.7 | B4: INSTALAÇÕES AR CONDICIONADO
A5: 6.7.1 | B5: 89865 | C5: TUBO, PVC, SOLDÁVEL, DN 25MM, INSTALADO EM DRENO DE AR-CONDICIONADO - FORNECIMENTO E INSTALAÇÃO. AF 12/2014 | E5: 65 | F5: 10.21 | G5: 12.84 | H5: =G5*E5 -> 834.6
A6: 6.7.2 | B6: 43200 COMPOSIÇÃO | C6: AR CONDICIONADO SPLIT ON/OFF, CASSETE (TETO), FRIO 4 VIAS 60000 BTUS/H, CLASSIFICAÇÃO ENERGÉTICA C - SECO PROCEL, GÁS HFC, CONTROLE S/ FIO | E6: 1 | F6: 11528.03 | G6: 14505.2 | H6: =G6*E6 -> 14505.2
E7: Total do item 6.7 | H7: =SUM(H5:H6) -> 15339.8

Sheet 6.8 INSTALAÇÕES SANITÁRIAS PLUV
A1: 6.8 INSTALAÇÕES SANITÁRIAS/PLUVIAIS
A2: ITEM | B2: REFERÊNCIA | C2: DISCRIMINAÇÃO | D2: UND | E2: QUANTIDADE | F2: PREÇO UNITÁRIO | H2: P. TOTAL
F3: SEM BDI | G3: COM BDI
A4: 6.8 | B4: INSTALAÇÕES SANITÁRIAS/PLUVIAIS
A5: 6.8.1 | B5: 89508 | C5: TUBO PVC, SÉRIE R, ÁGUA PLUVIAL, DN 40 MM, FORNECIDO E INSTALADO EM RAMAL DE ENCAMINHAMENTO. AF 12/2014 | D5: M | E5: 12.59 | F5: 18.49 | G5: 23.26 | H5: =G5*E5 -> 292.8434
A6: 6.8.2 | B6: 89509 | C6: TUBO PVC, SÉRIE R, ÁGUA PLUVIAL, DN 50 MM, FORNECIDO E INSTALADO EM RAMAL DE ENCAMINHAMENTO. AF 12/2014 | D6: M | E6: 17.96 | F6: 25.53 | G6: 32.12 | H6: =G6*E6 -> 576.8752
A7: 6.8.3 | B7: 89512 | C7: TUBO PVC, SÉRIE R, ÁGUA PLUVIAL, DN 100 MM, FORNECIDO E INSTALADO EM RAMAL DE ENCAMINHAMENTO. AF 12/2014 | D7: M | E7: 24.24 | F7: 60.55 | G7: 76.18 | H7: =G7*E7 -> 1846.6032
A8: 6.8.4 | B8: 98104 | C8: CAIXA DE GORDURA DUPLA EM CONCRETO PRÉ-MOLDADO DN 60 MM COM TAMPA - FORNECIMENTO E INSTALAÇÃO | E8: 1 | F8: 346.65 | G8: 436.17 | H8: =G8*E8 -> 436.17
E9: Total do item 6.8 | H9: =SUM(H5:H8) -> 3152.4918

Sheet 6.9 INSTALAÇÕES ELÉTRICAS
A1: 6.9 INSTALAÇÕES ELÉTRICAS
A2: ITEM | B2: REFERÊNCIA | C2: DISCRIMINAÇÃO | D2: UND | E2: QUANTIDADE | F2: PREÇO UNITÁRIO | H2: P. TOTAL
F3: SEM BDI | G3: COM BDI
A4: 6.9 | B4: INSTALAÇÕES ELÉTRICAS
A5: 6.9.1 | B5: 91924 | C5: CABO DE COBRE FLEXÍVEL ISOLADO, 1,5 MM², ANTI-CHAMA 450/750 V, PARA CIRCUITOS TERMINAIS – FORNECIMENTO E INSTALAÇÃO. | D5: M | E5: 21 | F5: 2.55 | G5: 3.2 | H5: =G5*E5 -> 67.2
A6: 6.9.2 | B6: 91926 | C6: CABO DE COBRE FLEXÍVEL ISOLADO, 2,5 MM², ANTI-CHAMA 450/750 V, PARA CIRCUITOS TERMINAIS – FORNECIMENTO E INSTALAÇÃO. AF 12/2015 | D6: M | E6: 120.65 | F6: 3.78 | G6: 4.75 | H6: =G6*E6 -> 573.0875
A7: 6.9.3 | B7: 91928 | C7: CABO DE COBRE FLEXÍVEL ISOLADO, 4 MM², ANTI-CHAMA 450/750 V, PARA CIRCUITOS TERMINAIS – FORNECIMENTO E INSTALAÇÃO. AF_12/2015 | D7: M | E7: 64.58 | F7: 6.32 | G7: 7.95 | H7: =G7*E7 -> 513.411
A8: 6.9.4 | B8: 91934 | C8: CABO DE COBRE FLEXÍVEL ISOLADO, 16 MM², ANTI-CHAMA 450/750 V, PARA CIRCUITOS TERMINAIS – FORNECIMENTO E INSTALAÇÃO. AF_12/2015 | D8: M | E8: 210 | F8: 22.19 | G8: 27.92 | H8: =G8*E8 -> 5863.2
A9: 6.9.5 | B9: 93657 | C9: DISJUNTOR MONOPOLAR TIPO DIN, CORRENTE NOMINAL DE 32A – FORNECIMENTO E INSTALAÇÃO. AF 10/2020 | D9: und | E9: 3 | F9: 13.05 | G9: 16.42 | H9: =G9*E9 -> 49.26
A10: 6.9.6 | B10: 101894 | C10: DISJUNTOR TERMOMAGNÉTICO TRIPOLAR PADRÃO NEMA (AMERICANO) 60 A 100A 24 OV, FORNECIMENTO E INSTALAÇÃO. | D10: und | E10: 2 | F10: 140.67 | G10: 176.99 | H10: =G10*E10 -> 353.98
A11: 6.9.7 | B11: 91849 | C11: ELETRODUTO FLEXÍVEL CORRUGADO, PVC, DN 32 MM PARA CIRCUITOS TERMINAIS, INSTALADO EM FORRO – FORNECIMENTO E INSTALAÇÃO. AF 12/2015 | D11: M | E11: 90.31 | F11: 5.67 | G11: 7.13 | H11: =G11*E11 -> 643.9103
A12: 6.9.8 | B12: 97593 | C12: LUMINÁRIA TIPO SPOT, DE SOBREPOR, COM 1 LÂMPADA FLUORESCENTE DE 15 W, SEM REATOR – FORNECIMENTO E INSTALAÇÃO. AF_02/2020 | D12: und | E12: 6 | F12: 123.1 | G12: 154.89 | H12: =G12*E12 -> 929.34
A13: 6.9.9 | B13: 92023 | C13: INTERRUPTOR SIMPLES (1 MÓDULO) COM 1 TOMADA DE EMBUTIR 2P+T 10 A, INCLUINDO SUPORTE E PLACA – FORNECIMENTO E INSTALAÇÃO. AF 12/2015 | D13: uni | E13: 8 | F13: 33.59 | G13: 42.26 | H13: =G13*E13 -> 338.08
A14: 6.9.10 | B14: 92027 | C14: INTERRUPTOR SIMPLES (2 MÓDULOS) COM 1 TOMADA DE EMBUTIR 2P+T 10 A, INCLUINDO SUPORTE E PLACA – FORNECIMENTO E INSTALAÇÃO. AF 12/2015 | D14: und | E14: 1 | F14: 44.71 | G14: 56.25 | H14: =G14*E14 -> 56.25
A15: 6.9.11 | B15: 101879 | C15: QUADRO DE DISTRIBUIÇÃO DE ENERGIA EM CHAPA DE AÇO GALVANIZADO, DE EMBUTIR, COM BARRAMENTO TRIFÁSICO, PARA 24 DISJUNTORES DIN 100A – FORNECIMENTO E INSTALAÇÃO. AF 10/2020 | D15: und | E15: 1 | F15: 588.48 | G15: 740.45 | H15: =G15*E15 -> 740.45
A16: 6.9.12 | B16: 100557 | C16: CAIXA DE PASSAGEM PARA TELEFONE 80X80X15CM (SOBREPOR) – FORNECIMENTO E INSTALAÇÃO. AF 11/2019 | D16: und | E16: 1 | F16: 483.28 | G16: 608.08 | H16: =G16*E16 -> 608.08
E17: Total do item 6.9 | H17: =SUM(H5:H16) -> 10736.249

Sheet 6.10 CALÇADA EXTERNA
A1: 6.10 CALÇADA EXTERNA
A2: ITEM | B2: REFERÊNCIA | C2: DISCRIMINAÇÃO | D2: UND | E2: QUANTIDADE | F2: PREÇO UNITÁRIO | H2: P. TOTAL
F3: SEM BDI | G3: COM BDI
A4: 6.10 | B4: CALÇADA EXTERNA
A5: 6.10.1 | B5: 92397 | C5: EXECUÇÃO DE PÁTIO/ESTACIONAMENTO EM PISO INTERTRAVADO, COM BLOCO RETANGULAR COR NATURAL DE 20 X 10 CM, ESPESSURA 6 CM. | E5: 53.6 | F5: 60.97 | G5: 76.71 | H5: =G5*E5 -> 4111.656
E6: Total do item 6.10 | H6: =SUM(H5) -> 4111.656
A8: TOTAL DO ITEM 6 | H8: =SUM(H6+'6.9 INSTALAÇÕES ELÉTRICAS'!H17+'6.8 INSTALAÇÕES SANITÁRIAS PLUV'!H9+'6.7 INSTALAÇÕES AR CONDICIONADO'!H7+'6.6 DIVISÓRIAS ACARTONADA'!H6+'6.5 COBERTURA'!H7+'6.4 PINTURA'!H8+'6.3 ESQUADRIAS DE VIDROS'!H7+'6.2 REVESTIMENTO DE PAREDES'!H6+'6.1 EDIFÍCIO CASA DE FORÇA'!H11) -> 126668.97

Sheet 7.1 MÓDULOS FOTOVOLTAICAS
A1: 7.1 MÓDULOS FOTOVOLTAICAS
A2: ITEM | B2: REFERÊNCIA | C2: DISCRIMINAÇÃO | D2: UND | E2: QUANTIDADE | F2: PREÇO UNITÁRIO | H2: P. TOTAL
F3: SEM BDI | G3: COM BDI
A4: 7.1 | B4: MÓDULOS FOTOVOLTAICAS
A5: 7.1.1 | B5: Composição | C5: Fornecimento e instalação de Gerador Fotovoltaico de 30.000KWp | D5: KWp | E5: 30000 | F5: 2727.27 | G5: 3431.72 | H5: =G5*E5 -> 102951600
E6: Total do item 7.1 | H6: =SUM(H5) -> 102951600

Sheet 7.2 INVERSORES
A1: 7.2 INVERSORES
A2: ITEM | B2: REFERÊNCIA | C2: DISCRIMINAÇÃO | D2: UND | E2: QUANTIDADE | F2: PREÇO UNITÁRIO | H2: P. TOTAL
F3: SEM BDI | G3: COM BDI
A4: 7.2 | B4: CALÇADA EXTERNA
A5: 7.2.1 | B5: Composição | C5: Fornecimento e instalação dos Inversores AC DC | D5: UND | E5: 84 | F5: 45000 | G5: 56623.5 | H5: =G5*E5 -> 4756374
E6: Total do item 7.2 | H6: =SUM(H5) -> 4756374

Sheet 7.3 ESTRUTURA DE SUPORTE METÁLI
A1: 7.3 ESTRUTURA DE SUPORTE METÁLICO
A2: ITEM | B2: REFERÊNCIA | C2: DISCRIMINAÇÃO | D2: UND | E2: QUANTIDADE | F2: PREÇO UNITÁRIO | H2: P. TOTAL
F3: SEM BDI | G3: COM BDI
A4: 7.3 | B4: CALÇADA EXTERNA
A5: 7.3.1 | B5: Composição | C5: Fornecimento e instalação de kit estrutura solo | D5: UND | E5: 50848 | F5: 250 | G5: 314.58 | H5: =G5*E5 -> 15995764
E6: Total do item 7.3 | H6: =SUM(H5) -> 15995764
A8: TOTAL DO ITEM 7 | H8: =SUM('7.1 MÓDULOS FOTOVOLTAICAS'!H6+'7.2 INVERSORES'!H6+'7.3 ESTRUTURA DE SUPORTE METÁLI'!H6) -> 1.2370374e+08

Sheet 8.1 INSTALAÇÕES ELÉTRICAS EXTER
A1: 8 INSTALAÇÕES ELÉTRICAS EXTERNAS
A2: ITEM | B2: REFERÊNCIA | C2: DISCRIMINAÇÃO | D2: UND | E2: QUANTIDADE | F2: PREÇO UNITÁRIO | H2: P. TOTAL
F3: SEM BDI | G3: COM BDI
A4: 8.1 | B4: INSTALAÇÕES ELÉTRICAS EXTERNAS
A5: 8.1 | B5: 102302 | C5: ESCAVAÇÃO MECANIZADA DE VALA COM PROF. ATÉ 1,5 M (MÉDIA ENTRE MONTANTE E JUSANTE/UMA COMPOSIÇÃO POR TRECHO) COM RETROESCAVADEIRA (0,26 M3/188 HP), LARG. MENOR QUE 0,8 M, EM SOLO MOLE, LOCAIS COM BAIXO NÍVEL DE INTERFERÊNCIA. AF 02/2021 | E5: 62256.5 | F5: 6.57 | G5: 8.26 | H5: =G5*E5 -> 514238.69
A6: 8.2 | B6: 93368 | C6: REATERRO MECANIZADO DE VALA COM ESCAVADEIRA HIDRÁULICA (CAPACIDADE DA CAÇAMBA: 0,8 M3 / POTÊNCIA: 111 HP), LARGURA ATÉ 1,5 M, PROFUNDIDADE E A 3,0 M, COM SOLO DE 1ª CATEGORIA EM LOCAIS COM BAIXO NÍVEL DE INTERFERÊNCIA. AF 04/2016 | E6: 62256.5 | F6: 11.6 | G6: 14.59 | H6: =G6*E6 -> 908322.33
F7: Total do item 8 | H7: =SUM(H5:H6) -> 1422561
A9: TOTAL DO ITEM 8 | H9: =H7 -> 1422561

Sheet 9 SUBESTAÇÃO_x0009__x0009_
A1: 9 SUBESTAÇÃO
A2: ITEM | B2: REFERÊNCIA | C2: DISCRIMINAÇÃO | D2: UND | E2: QUANTIDADE | F2: PREÇO UNITÁRIO | H2: P. TOTAL
F3: SEM BDI | G3: COM BDI
A4: 9.1 | B4: INSTALAÇÕES ELÉTRICAS EXTERNAS
A5: 9.1 | B5: Composição | C5: Subestação não abrigada 380/34,5KV 2.500Va | D5: und | E5: 10 | F5: 700000 | G5: 880778.54 | H5: =G5*E5 -> 8807785.4
A6: 9.2 | B6: Composição | C6: Subestação Principal 25.000KVA, conecxao em 380/34,5KV, ou 69KV, ou 134KV | D6: und | E6: 1 | F6: 16000000 | G6: 20128000 | H6: =G6*E6 -> 20128000
F7: Total do item 9 | H7: =SUM(H5:H6) -> 28935785

Sheet 10 ADMINISTRAÇÃO
A1: 10 ADMINISTRAÇÃO
A2: ITEM | B2: REFERÊNCIA | C2: DISCRIMINAÇÃO | D2: UND | E2: QUANTIDADE | F2: PREÇO UNITÁRIO | H2: P. TOTAL
F3: SEM BDI | G3: COM BDI
A4: 10 | B4: ADMINISTRAÇÃO
A5: 10.1 | B5: 93567 | C5: ENGENHEIRO DE OBRA PLENO (IH DIA) | D5: MÊS | E5: 8 | F5: 20000 | G5: 25160 | H5: =G5*E5 -> 201280
A6: 10.2 | B6: 90780 | C6: MESTRE DE OBRAS | D6: MÊS | E6: 8 | F6: 10000 | G6: 12580 | H6: =G6*E6 -> 100640
A7: 10.3 | B7: 88326 | C7: VIGIA NOTURNO (8H DIA) | D7: MÊS | E7: 8 | F7: 38500 | G7: 48433 | H7: =G7*E7 -> 387464
A8: 10.4 | B8: 94296 | C8: TOPÓGRAFO COM ENCARGOS COMPLEMENTARES | D8: MÊS | E8: 8 | F8: 8000 | G8: 10064 | H8: =G8*E8 -> 80512
F9: Total do item 10 | H9: =SUM(H5:H8) -> 769896
A11: Total do item 10 | H11: 769896

Sheet TOTAL GERAL
A1: TOTAL GERAL
A2: ='PLAN.FIN.CAD02'!C33 -> 2.8113282e+08

Sheet PLAN.FIN.CAD02
A1: Item | B1: Descrição | C1: TOTAL | D1: 1 | E1: 2 | F1: 3 | G1: 4 | H1: 5 | I1: 6 | J1: 7 | K1: 8 | L1: TOTAL | M1: PERCENTUAL (%)
A2: 0.1 | B2: RESSARCIMENTO CUSTOS ESTUDOS VIAB. | C2: =PROJ.VIABILIDADE!G8 -> 1258000 | D2: =C2 -> 1258000 | E2: - | F2: - | G2: - | H2: - | I2: - | J2: - | K2: - | L2: =SUM(D2:K2) -> 1258000 | M2: =L2/L33*100 -> 0.44747533
A3: 1.0 | B3: PLANILHA ORÇAMENTÁRIA | C3: ='1.0 PLANILHA ORÇAMENTARIA'!H33 -> 746403.4 | D3: =C3/2 -> 373201.7 | E3: =C3-D3 -> 373201.7 | F3: - | G3: - | H3: - | I3: - | J3: - | K3: - | L3: =SUM(D3:K3) -> 746403.4 | M3: =L3/L33*100 -> 0.26549849
A4: 2.0 | B4: MOVIMENTO DE TERRA E DRENAGEM | C4: ='2.0 MOVIMENTO DE TERRA E DREN'!H14 -> 3355370 | D4: - | E4: =C4 -> 3355370 | F4: - | G4: - | H4: - | I4: - | J4: - | K4: - | L4: =C4 -> 3355370 | M4: =L4/L33*100 -> 1.1935177
A5: 3.0 | B5: CERCAMENTO DO TERRENO | C5: ='3.1 CERCAMENTO DO TERRENO'!H11 -> 457112.5 | D5: - | E5: - | F5: =C5 -> 457112.5 | G5: - | H5: - | I5: - | J5: - | K5: - | L5: =SUM(F5:K5) -> 457112.5 | M5: =L5/L33*100 -> 0.16259663
A6: 4.0 | B6: FUNDAÇÃO DAS ESTRUTURAS DOS PAINÉIS | C6: ='4.1 FUNDAÇÃO ESTRUTURAS PAINEIS'!H10 -> 12074842 | D6: - | E6: =C6/2 -> 6037421 | F6: =C6-E6 -> 6037421 | G6: - | H6: - | I6: - | J6: - | K6: - | L6: =SUM(E6:K6) -> 12074842 | M6: =L6/L33*100 -> 4.2950667
A7: 5.0 | B7: EDIFICIOS ESCRITÓRIO E ALMOXARIFADO | C7: ='5.1 EDIFICIOS ESCRITÓRIO E ALMO'!H24 -> 51446.076 | D7: - | E7: =C7 -> 51446.076 | F7: - | G7: - | H7: - | I7: - | J7: - | K7: - | L7: =SUM(E7:K7) -> 51446.076 | M7: =L7/L33*100 -> 0.018299562
A8: 5.2 | B8: REVESTIMENTO DE PAREDES E LAJES | C8: ='5.2 REVESTIMENTO DE PAREDES'!H14 -> 7079.238 | D8: - | E8: =C8 -> 7079.238 | F8: - | G8: - | H8: - | I8: - | J8: - | K8: - | L8: =SUM(E8:K8) -> 7079.238 | M8: =L8/L33*100 -> 0.0025181116
A9: 5.3 | B9: ESQUADRIAS DE MADEIRA | C9: ='5.3 ESQUADRIAS DE MADEIRA'!H21 -> 5964.9476 | D9: - | E9: =C9 -> 5964.9476 | F9: - | G9: - | H9: - | I9: - | J9: - | K9: - | L9: =SUM(E9:K9) -> 5964.9476 | M9: =L9/L33*100 -> 0.0021217543
A10: 5.4 | B10: PINTURA/ACABAMENTO | C10: ='5.4 PINTURA ACABAMENTO'!H14 -> 14625.633 | D10: - | E10: =C10 -> 14625.633 | F10: - | G10: - | H10: - | I10: - | J10: - | K10: - | L10: =SUM(E10:K10) -> 14625.633 | M10: =L10/L33*100 -> 0.0052023928
A11: 5.5 | B11: COBERTURA | C11: ='5.5 COBERTURA'!H13 -> 40196.823 | D11: - | E11: =C11 -> 40196.823 | F11: - | G11: - | H11: - | I11: - | J11: - | K11: - | L11: =SUM(E11:K11) -> 40196.823 | M11: =L11/L33*100 -> 0.014298161
A12: 5.6 | B12: FORROS E DIVISORIAS | C12: ='5.6 FORROS E DIVISORIAS'!H8 -> 6314.697 | D12: - | E12: =C12 -> 6314.697 | F12: - | G12: - | H12: - | I12: - | J12: - | K12: - | L12: =SUM(E12:K12) -> 6314.697 | M12: =L12/L33*100 -> 0.0022461615
A13: 5.7 | B13: INSTALACOES HIDRAULICAS | C13: ='5.7 INSTALACOES HIDRAULICAS'!H24 -> 10956.28 | D13: - | E13: =C13 -> 10956.28 | F13: - | G13: - | H13: - | I13: - | J13: - | K13: - | L13: =SUM(E13:K13) -> 10956.28 | M13: =L13/L33*100 -> 0.00389719
A14: 5.8 | B14: INSTALACOES SANITARIAS/PLUVIAIS | C14: ='5.8 INSTALACOES SANITARIAS PLU'!H14 -> 13870.047 | D14: - | E14: =C14 -> 13870.047 | F14: - | G14: - | H14: - | I14: - | J14: - | K14: - | L14: =SUM(E14:K14) -> 13870.047 | M14: =L14/L33*100 -> 0.0049336278
A15: 5.9 | B15: INSTALAÇÓES ELÉTRICAS | C15: ='5.9 INSTALAÇÓES ELÉTRICAS'!H17 -> 20467.009 | D15: - | E15: =C15 -> 20467.009 | F15: - | G15: - | H15: - | I15: - | J15: - | K15: - | L15: =SUM(E15:K15) -> 20467.009 | M15: =L15/L33*100 -> 0.0072801918
A16: 5.10 | B16: CALÇADA EXTERNA | C16: {='5.10 CALÇADA EXTERNA'!H11:H11} -> 280988.94 | D16: - | E16: =C16 -> 280988.94 | F16: - | G16: - | H16: - | I16: - | J16: - | K16: - | L16: =SUM(E16:K16) -> 280988.94 | M16: =L16/L33*100 -> 0.099948823
A17: 6.1 | B17: EDIFÍCIO CASA DE FORÇA (INVERSORES) | C17: ='6.1 EDIFÍCIO CASA DE FORÇA'!H11 -> 26749.749 | D17: - | E17: =C17 -> 26749.749 | F17: - | G17: - | H17: - | I17: - | J17: - | K17: - | L17: =SUM(E17:K17) -> 26749.749 | M17: =L17/L33*100 -> 0.0095149861
A18: 6.2 | B18: REVESTIMENTO DE PAREDES E LAJES | C18: ='6.2 REVESTIMENTO DE PAREDES'!H6 -> 2293.92 | D18: - | E18: =C18 -> 2293.92 | F18: - | G18: - | H18: - | I18: - | J18: - | K18: - | L18: =SUM(E18:K18) -> 2293.92 | M18: =L18/L33*100 -> 0.00081595597
A19: 6.3 | B19: ESQUADRIAS DE VIDROS | C19: ='6.3 ESQUADRIAS DE VIDROS'!H7 -> 3399.048 | D19: - | E19: =C19 -> 3399.048 | F19: - | G19: - | H19: - | I19: - | J19: - | K19: - | L19: =SUM(E19:K19) -> 3399.048 | M19: =L19/L33*100 -> 0.0012090541
A20: 6.4 | B20: PINTURA/PREPARAÇÃO | C20: ='6.4 PINTURA'!H8 -> 17733.857 | D20: - | E20: =C20 -> 17733.857 | F20: - | G20: - | H20: - | I20: - | J20: - | K20: - | L20: =SUM(E20:K20) -> 17733.857 | M20: =L20/L33*100 -> 0.0063079994
A21: 6.5 | B21: COBERTURA/MADEIRAMENTO | C21: ='6.5 COBERTURA'!H7 -> 36972.678 | D21: - | E21: =C21 -> 36972.678 | F21: - | G21: - | H21: - | I21: - | J21: - | K21: - | L21: =SUM(E21:K21) -> 36972.678 | M21: =L21/L33*100 -> 0.013151321
A22: 6.6 | B22: DIVISÓRIAS ACARTONADA | C22: ='6.6 DIVISÓRIAS ACARTONADA'!H6 -> 6179.52 | D22: - | E22: =C22 -> 6179.52 | F22: - | G22: - | H22: - | I22: - | J22: - | K22: - | L22: =SUM(E22:K22) -> 6179.52 | M22: =L22/L33*100 -> 0.0021980785
A23: 6.7 | B23: INSTALAÇÕES AR CONDICIONADO | C23: ='6.7 INSTALAÇÕES AR CONDICIONADO'!H7 -> 15339.8 | D23: - | E23: =C23 -> 15339.8 | F23: - | G23: - | H23: - | I23: - | J23: - | K23: - | L23: =SUM(E23:K23) -> 15339.8 | M23: =L23/L33*100 -> 0.0054564245
A24: 6.8 | B24: INSTALAÇÕES SANITÁRIAS/PLUVIAIS | C24: ='6.8 INSTALAÇÕES SANITÁRIAS PLUV'!H9 -> 3152.4918 | D24: - | E24: =C24 -> 3152.4918 | F24: - | G24: - | H24: - | I24: - | J24: - | K24: - | L24: =SUM(E24:K24) -> 3152.4918 | M24: =L24/L33*100 -> 0.0011213532
A25: 6.9 | B25: INSTALAÇÕES ELÉTRICAS INTERNAS | C25: ='6.9 INSTALAÇÕES ELÉTRICAS'!H17 -> 10736.249 | D25: - | E25: =C25 -> 10736.249 | F25: - | G25: - | H25: - | I25: - | J25: - | K25: - | L25: =SUM(E25:K25) -> 10736.249 | M25: =L25/L33*100 -> 0.003818924
A26: 6.10 | B26: CALÇADA EXTERNA | C26: {='6.10 CALÇADA EXTERNA'!H8:H8} -> 126668.97 | D26: - | E26: =C26 -> 126668.97 | F26: - | G26: - | H26: - | I26: - | J26: - | K26: - | L26: =SUM(E26:K26) -> 126668.97 | M26: =L26/L33*100 -> 0.045056628
A27: 7.1 | B27: MÓDULOS FOTOVOLTAICAS | C27: ='7.1 MÓDULOS FOTOVOLTAICAS'!H6 -> 102951600 | D27: - | E27: - | F27: =C27 -> 102951600 | G27: - | H27: - | I27: - | J27: - | K27: - | L27: =SUM(E27:K27) -> 102951600 | M27: =L27/L33*100 -> 36.620271
A28: 7.2 | B28: INVERSORES | C28: ='7.2 INVERSORES'!H6 -> 4756374 | D28: - | E28: =C28 -> 4756374 | F28: - | G28: - | H28: - | I28: - | J28: - | K28: - | L28: =SUM(E28:K28) -> 4756374 | M28: =L28/L33*100 -> 1.6918601
A29: 7.3 | B29: ESTRUTURA DE SOLO - USINA SOLAR | C29: {='7.3 ESTRUTURA DE SUPORTE METÁLI'!H8:H8} -> 1.2370374e+08 | D29: - | E29: =C29 -> 1.2370374e+08 | F29: - | G29: - | H29: - | I29: - | J29: - | K29: - | L29: =SUM(E29:K29) -> 1.2370374e+08 | M29: =L29/L33*100 -> 44.001884
A30: 8.1 | B30: INSTALAÇÕES ELÉTRICAS EXTERNAS | C30: ='8.1 INSTALAÇÕES ELÉTRICAS EXTER'!H9 -> 1422561 | D30: - | E30: =C30 -> 1422561 | F30: - | G30: - | H30: - | I30: - | J30: - | K30: - | L30: =SUM(E30:K30) -> 1422561 | M30: =L30/L33*100 -> 0.5060103
A31: 9 | B31: SUBESTAÇÃO | C31: ='9 SUBESTAÇÃO '!H7 -> 28935785 | D31: =C31 -> 28935785 | E31: - | F31: - | G31: - | H31: - | I31: - | J31: - | K31: - | L31: =D31 -> 28935785 | M31: =L31/L33*100 -> 10.292568
A32: 10 | B32: ADMINISTRAÇÃO | C32: ='10 ADMINISTRAÇÃO'!H11 -> 769896 | D32: =C32/8 -> 96237 | E32: =C32/8 -> 96237 | F32: =C32/8 -> 96237 | G32: =C32/8 -> 96237 | H32: =C32/8 -> 96237 | I32: =C32/8 -> 96237 | J32: =C32/8 -> 96237 | K32: =C32-D32-E32-F32-G32-H32-I32-J32 -> 96237 | L32: =SUM(D32:K32) -> 769896 | M32: =L32/L33*100 -> 0.2738549
A33: Total | C33: =SUM(C2:C32) -> 2.8113282e+08 | D33: =SUM(D2:D32) -> 30663224 | E33: =SUM(E2:E32) -> 1.4044604e+08 | F33: =SUM(F2:F32) -> 1.0954237e+08 | G33: =SUM(G2:G32) -> 96237 | H33: =SUM(H2:H32) -> 96237 | I33: =SUM(I2:I32) -> 96237 | J33: =SUM(J2:J32) -> 96237 | ... M33: =SUM(M2:M32) -> 100

Sheet QUADRO DE RECEITAS
A1: item | B1: Receitas totais energia elétrica liquida | C1: Ref. | D1: Ano Incio | E1: Ano 1 | F1: Ano 2 | G1: Ano 3 | H1: Ano 4 | I1: ano 5 | J1: Ano 6 | K1: Ano 7 | L1: Ano 8 | M1: Ano 9 | N1: Ano 10 | O1: Ano 11 | P1: Ano 12 | Q1: Ano 13 | R1: Ano 14 | S1: Ano 15 | T1: Ano 20 | U1: Ano 25
A2: 1 | B2: Capacidade de Produção | D2: 48000000 | E2: 48000000 | F2: 48000000 | G2: 48000000 | H2: 48000000 | I2: 48000000 | J2: 48000000 | K2: 48000000 | L2: 48000000 | M2: 48000000 | N2: 48000000 | O2: 48000000 | P2: 48000000 | Q2: 48000000 | R2: 48000000 | S2: 48000000 | T2: 48000000 | U2: 48000000
A3: 2 | B3: Índice de redução de eficiencia (% a.a) 25 anos | C3: 1 | D3: 1 | E3: 0.992 | F3: 0.984 | G3: 0.976 | H3: 0.968 | I3: 0.96 | J3: 0.952 | K3: 0.944 | L3: 0.936 | M3: 0.928 | N3: 0.92 | O3: 0.912 | P3: 0.904 | Q3: 0.896 | R3: 0.888 | S3: 0.88 | T3: 0.84 | U3: 0.8
A4: 3 | B4: Qtde. Liquida produzida | C4: KW/h | D4: 48000000 | E4: =D4*E3/100 -> 476160 | F4: =D4*F3/100 -> 472320 | G4: =D4*G3/100 -> 468480 | H4: =D4*H3/100 -> 464640 | I4: =D4*I3/100 -> 460800 | J4: =D4*J3/100 -> 456960 | K4: =D4*K3/100 -> 453120 | L4: =D4*L3/100 -> 449280 | M4: =D4*M3/100 -> 445440 | N4: =D4*N3/100 -> 441600 | O4: =D4*O3/100 -> 437760 | P4: =D4*P3/100 -> 433920 | Q4: =D4*Q3/100 -> 430080 | R4: =D4*R3/100 -> 426240 | S4: =D4*S3/100 -> 422400 | T4: =D4*T3/100 -> 403200 | U4: =D4*U3/100 -> 384000
A5: 4 | B5: Taxa de energia consumida pelo município | D5: 1 | E5: 1 | F5: 1 | G5: 1 | H5: 1 | I5: 1 | J5: 1 | K5: 1 | L5: 1 | M5: 1 | N5: 1 | O5: 1 | P5: 1 | Q5: 1 | R5: 1 | S5: 1 | T5: 1 | U5: 1
A6: 5 | B6: Valor unitáno poder público (R$) | C6: 0.88 | D6: 0.88 | E6: 0.88 | F6: 0.88 | G6: 0.88 | H6: 0.88 | I6: 0.88 | J6: 0.88 | K6: 0.88 | L6: 0.88 | M6: 0.88 | N6: 0.88 | O6: 0.88 | P6: 0.88 | Q6: 0.88 | R6: 0.88 | S6: 0.88 | T6: 0.88 | U6: 0.88
A7: 6 | B7: Valor total do consumo poder público | D7: =C6*D4 -> 42240000 | E7: 42240000 | F7: 42240000 | G7: 42240000 | H7: 42240000 | I7: 42240000 | J7: 42240000 | K7: 42240000 | L7: 42240000 | M7: 42240000 | N7: 42240000 | O7: 42240000 | P7: 42240000 | Q7: 42240000 | R7: 42240000 | S7: 42240000 | T7: 42240000 | U7: 42240000
A8: 7 | B8: Valor unitario Receita com desconto 10% | C8: 0.8 | D8: 0.8 | E8: 0.8 | F8: 0.8 | G8: 0.8 | H8: 0.8 | I8: 0.8 | J8: 0.8 | K8: 0.8 | L8: 0.8 | M8: 0.8 | N8: 0.8 | O8: 0.8 | P8: 0.8 | Q8: 0.8 | R8: 0.8 | S8: 0.8 | T8: 0.8 | U8: 0.8
A9: 8 | B9: Valor outras receitas | C9: - | D9: - | E9: - | F9: - | G9: - | H9: - | I9: - | J9: - | K9: - | L9: - | M9: - | N9: - | O9: - | P9: - | Q9: - | R9: - | S9: - | T9: - | U9: -
A10: 9 | B10: Valor unitario das receitas | C10: 0.8 | D10: =C10*D4 -> 38400000 | E10: 38400000 | F10: 38400000 | G10: 38400000 | H10: 38400000 | I10: 38400000 | J10: 38400000 | K10: 38400000 | L10: 38400000 | M10: 38400000 | N10: 38400000 | O10: 38400000 | P10: 38400000 | Q10: 38400000 | R10: 38400000 | S10: 38400000 | T10: 38400000 | U10: 38400000
A11: 10 | B11: Receitas totais *
A12: 11 | B12: *Receitas totais com medição a geração de energia com depreciação de geraçao sem os aumentos previstos no Caderno de desempenho Item 5 (5.3)
A13: * 5.1 A PARCELA REMUNERATÓRIA MENSAL corresponde ao valor estabelecido para o VALOR DE CONTRAPRESTAÇÃO MENSAL que a LICITANTE espera receber, definido a partir do lance vencedor do certame, conforme identificado no CONTRATO. 5.2 O valor do CONTRATO será estabelecido a partir da PARCELA REMUNERATÓRIA MENSAL acumulada para o período de vigência da OPERAÇÃO da(s) USINA(S) SOLAR(ES) FOTOVOLTAICA(S), o que corresponde ao total de 300 (trezentos) PARCELAS REMUNERATÓRIAS MENSAIS. 5.3 O valor da PARCELA REMUNERATÓRIA MENSAL será reajustado a cada doze meses de CONTRATO, sendo 50% pela variação anual do IPC-A e 50% pela variação anual do IGPM; ou outro índice que vier a substitui-lo.

Sheet CUSTOS E DESPESAS ADM-OPER.
A1: CUSTOS E DESPESAS ADMINISTRATIVAS/OPERACIONAIS
B3: Mensal | C3: Anual
A4: Agua e esgoto | B4: 1000 | C4: =B4*12 -> 12000
A5: Energia | C5: =B5*12 -> 0
A6: Telefone / Internet | B6: 1000 | C6: =B6*12 -> 12000
A7: Material de Limpeza/consumo | B7: 2000 | C7: =B7*12 -> 24000
A8: Honorarios contabeis | B8: 10000 | C8: =B8*12 -> 120000
A9: Honorários advocatícios | B9: 10000 | C9: =B9*12 -> 120000
A10: Associa -es de classe | B10: 500 | C10: =B10*12 -> 6000
A11: Propaganda, publicidade e patrocínio | B11: 5000 | C11: =B11*12 -> 60000
A12: Outras despesas contingenciadas | B12: 10000 | C12: =B12*12 -> 120000
A13: Manutenção de ar condicionado (contrato mensal) | B13: 1000 | C13: =B13*12 -> 12000
A14: Aluguel de software | B14: 2500 | C14: =B14*12 -> 30000
A15: Seguro obra Civil - durante a obra | C15: =B15*12 -> 0
A16: Seguro Patrimonial- durante contrato | B16: 50000 | C16: =B16*12 -> 600000
A17: Seguro de veículos | B17: 1200 | C17: =B17*12 -> 14400
A18: Aluguel Equipamentos | B18: 1000 | C18: =B18*12 -> 12000
A19: Bens de uso de pequeno valor | B19: 250 | C19: =B19*12 -> 3000
A20: Material de Escritório | B20: 250 | C20: =B20*12 -> 3000
A21: Despesas com correios e fretes | B21: 50 | C21: =B21*12 -> 600
A22: Despesas com veículos (manut e combustiveis | B22: 2000 | C22: =B22*12 -> 24000
A23: Lanches e refeições | B23: 4000 | C23: =B23*12 -> 48000
A24: IPTU | B24: 85 | C24: =B24*12 -> 1020
A25: IPVA/Seguro/licenciamento veículos | B25: 416.67 | C25: =B25*12 -> 5000.04
A26: IOF | C26: =B26*12 -> 0
A27: Taxa de alvará | B27: 50 | C27: =B27*12 -> 600
A28: Demais impostos, taxas e emolumentos | B28: 500 | C28: =B28*12 -> 6000
A29: Depreciação e amortização do setor de geração Módulos de geração de energia fotovoltaica (25 anos) Ref. R$ 102.951.600,00 | B29: 68634 | C29: =B29*12 -> 823608
A30: Depreciação e amortização do setor de geração Inversores (10 anos) Ref. R$ 4.756.374,00 | B30: 7927.29 | C30: =B30*12 -> 95127.48
A31: DESPESAS COM PESSOAL
A32: Salários e ordenados | B32: 31000 | C32: =B32*12 -> 372000
A33: Prö labore | C33: =B33*12 -> 0
A34: Encargos sociais FGTS/INSS+encargos sociais | B34: 24800 | C34: =B34*12 -> 297600
B35: =SUM(B4:B34) -> 235162.96 | C35: =SUM(C4:C34) -> 2821955.5

Sheet FORMAÇÃO CUSTO KWh
A1: FORMAÇÃO DO CUSTO UNITÁRIO POR KWh
A2: Custos e tributos | B2: Indices de custos
A3: Provisão para IPRJ
A4: Provisão para CSLL
A5: ICMS s vendas
A6: PIS e COFINS
A7: ISS
A8: Taxa de Fiscalização de Serviço de Energia Elétrica (TFSEE)
A9: Taxa de regularização/fiscalização
A10: Total dos custos e despesas
A12: Custos e despesas totais mensais | B12: R$
A13: Produção total de energia no mês em KWh
A14: Custo unitario sem impostos e margem de lucro
A15: Custos variaveis
A16: Margem de lucro desejada
A17: Preço de venda

Sheet FLUXO CAIXA
B1: Receita | C1: Custos | D1: Custos | E1: EBITDA (R$) | F1: Impostos (R$) | G1: Fluxo de Caixa | H1: Fluxo de Caixa
B2: Bruta (R$) | C2: Operacionais (R$) | D2: Financeiros (R$) | G2: Simples (R$) | H2: Descontado (R$)
A3: Ano 1 | B3: 38400000 | C3: 2821955.5 | D3: 12983179 | E3: 22594865 | F3: 6552510.9 | G3: 16042354 | H3: 14355574
A4: Ano 2 | B4: 38400000 | C4: 2821955.5 | D4: 12983179 | E4: 22594865 | F4: 6552510.9 | G4: 16042354 | H4: 12846151
A5: Ano 3 | B5: 38400000 | C5: 2821955.5 | D5: 12983179 | E5: 22594865 | F5: 6552510.9 | G5: 16042354 | H5: 11495438
A6: Ano 4 | B6: 38400000 | C6: 2821955.5 | D6: 12983179 | E6: 22594865 | F6: 6552510.9 | G6: 16042354 | H6: 10286745
A7: Ano 5 | B7: 38400000 | C7: 2821955.5 | D7: 12983179 | E7: 22594865 | F7: 6552510.9 | G7: 16042354 | H7: 9205140.9
A8: Ano 6 | B8: 38400000 | C8: 2821955.5 | D8: 12983179 | E8: 22594865 | F8: 6552510.9 | G8: 16042354 | H8: 8237262.6
A9: Ano 7 | B9: 38400000 | C9: 2821955.5 | D9: 12983179 | E9: 22594865 | F9: 6552510.9 | G9: 16042354 | H9: 7371152.2
A10: Ano 8 | B10: 38400000 | C10: 2821955.5 | D10: 12983179 | E10: 22594865 | F10: 6552510.9 | G10: 16042354 | H10: 6596109.3
A11: Ano 9 | B11: 38400000 | C11: 2821955.5 | D11: 12983179 | E11: 22594865 | F11: 6552510.9 | G11: 16042354 | H11: 5902558.7
A12: Ano 10 | B12: 38400000 | C12: 2821955.5 | D12: 12983179 | E12: 22594865 | F12: 6552510.9 | G12: 16042354 | H12: 5281931.7
A13: Ano 11 | B13: 38400000 | C13: 2821955.5 | D13: 12983179 | E13: 22594865 | F13: 6552510.9 | G13: 16042354 | H13: 4726560.8
A14: Ano 12 | B14: 38400000 | C14: 2821955.5 | D14: 12983179 | E14: 22594865 | F14: 6552510.9 | G14: 16042354 | H14: 4229584.6
... A27: Ano 25 | B27: 38400000 | C27: 2821955.5 | D27: 12983179 | E27: 22594865 | F27: 6552510.9 | G27: 16042354 | H27: 997883.42

Sheet FLUXO CAIXA DESCONTADO
A1: ANO | B1: FC Simples (R$) | C1: Acumulado | D1: FC Descontado (R$) | E1: Acumulado
C2: Simples (R$) | E2: Descontado (R$)
A3: 1 | B3: 16042354 | C3: 16042354 | D3: 14355574 | E3: 14355574
A4: 2 | B4: 16042354 | C4: 32084708 | D4: 12846151 | E4: 27201726
A5: 3 | B5: 16042354 | C5: 48127063 | D5: 11495438 | E5: 38697163
A6: 4 | B6: 16042354 | C6: 64169417 | D6: 10286745 | E6: 48983908
A7: 5 | B7: 16042354 | C7: 80211771 | D7: 9205140.9 | E7: 58189049
A8: 6 | B8: 16042354 | C8: 96254125 | D8: 8237262.6 | E8: 66426312
A9: 7 | B9: 16042354 | C9: 1.1229648e+08 | D9: 7371152.2 | E9: 73797464
A10: 8 | B10: 16042354 | C10: 1.2833883e+08 | D10: 6596109.3 | E10: 80393573
A11: 9 | B11: 16042354 | C11: 1.4438119e+08 | D11: 5902558.7 | E11: 86296132
A12: 10 | B12: 16042354 | C12: 1.6042354e+08 | D12: 5281931.7 | E12: 91578064
A13: 11 | B13: 16042354 | C13: 1.764659e+08 | D13: 4726560.8 | E13: 96304624
A14: 12 | B14: 16042354 | C14: 1.9250825e+08 | D14: 4229584.6 | E14: 1.0053421e+08
... A27: 25 | B27: 16042354 | C27: 4.0105885e+08 | D27: 997883.42 | E27: 1.2803805e+08
